darkpoint/__init__.py
darkpoint/helpers.py
darkpoint/point_declaration.py
darkpoint-0.2.0.dist-info/LICENSE
darkpoint-0.2.0.dist-info/METADATA
darkpoint-0.2.0.dist-info/WHEEL
darkpoint-0.2.0.dist-info/top_level.txt
darkpoint-0.2.0.dist-info/RECORD
