Metadata-Version: 2.1
Name: darkpoint
Version: 0.2.0
Summary: This Python framework is technomantic mnemonic toolkit of thought model system with singular principles that allows to create memory palace with start placing in darkness.
Author-email: Sett Sarverott <sett@sarverott.com>
Maintainer-email: Sett Sarverott <sett@sarverott.com>
License: GNU GENERAL PUBLIC LICENSE
Project-URL: Homepage, https://github.com/sarverott/darkpoint
Project-URL: Issues, https://github.com/sarverott/darkpoint/issues
Keywords: dark,darkness,memory
Classifier: Programming Language :: Python :: 3
Classifier: License :: OSI Approved :: GNU General Public License v3 (GPLv3)
Classifier: Operating System :: OS Independent
Classifier: Natural Language :: English
Classifier: Natural Language :: Polish
Classifier: Development Status :: 1 - Planning
Classifier: Environment :: Plugins
Classifier: Environment :: Console
Classifier: Intended Audience :: Developers
Classifier: Intended Audience :: Education
Classifier: Intended Audience :: Science/Research
Classifier: Intended Audience :: Religion
Classifier: Programming Language :: Python :: Implementation
Classifier: Programming Language :: Python
Classifier: Topic :: Adaptive Technologies
Classifier: Topic :: Artistic Software
Classifier: Topic :: Communications
Classifier: Topic :: Database
Classifier: Topic :: Education
Classifier: Topic :: Religion
Classifier: Topic :: Scientific/Engineering
Classifier: Topic :: Scientific/Engineering :: Artificial Intelligence
Classifier: Topic :: Scientific/Engineering :: Artificial Life
Classifier: Topic :: Scientific/Engineering :: Information Analysis
Classifier: Topic :: Scientific/Engineering :: Physics
Classifier: Topic :: Scientific/Engineering :: Visualization
Classifier: Topic :: Sociology
Classifier: Topic :: Sociology :: History
Classifier: Topic :: Software Development
Classifier: Topic :: Software Development :: Documentation
Classifier: Topic :: Software Development :: Libraries
Classifier: Topic :: Software Development :: Libraries :: Python Modules
Classifier: Topic :: Software Development :: Libraries :: Application Frameworks
Classifier: Topic :: System
Classifier: Topic :: System :: Archiving
Classifier: Topic :: System :: Archiving :: Compression
Classifier: Topic :: System :: Clustering
Classifier: Topic :: System :: Emulators
Classifier: Topic :: System :: Filesystems
Classifier: Topic :: System :: Networking
Classifier: Topic :: System :: Operating System
Classifier: Topic :: System :: Software Distribution
Requires-Python: >=3.8
License-File: LICENSE
